tlc.v
module tlc (
    input clk,rst,
    output reg A_red,A_yellow, A_green,
    output reg B_red, B_yellow, B_green
);

parameter S0 = 4'b0001;
parameter S1 = 4'b0010;
parameter S2 = 4'b0100;
parameter S3 = 4'b1000;

parameter T_GREEN  = 10;
parameter T_YELLOW = 3;

reg [3:0] current_state, next_state;
reg [3:0] max_time, timer;


always @(posedge clk or posedge rst) begin
    if (rst) current_state <= S0;
    else current_state <= next_state;
end

always @(*) begin
    A_green = 0;
    A_red = 0;
    A_yellow = 0;
    B_green = 0;
    B_red = 0;
    B_yellow = 0;
    case (current_state)
        S0 : begin
            A_green = 1;
            B_red = 1;
        end
        S1 : begin
            A_yellow = 1;
            B_red = 1;
        end
        S2 : begin
            A_red = 1;
            B_green = 1;
        end
        S3 : begin
            A_red = 1;
            B_yellow = 1;
        end
        default: begin
            A_red = 1;
            B_red = 1;
        end
    endcase
end

always @(*) begin
    case (current_state)
        S0: max_time = T_GREEN;
        S1: max_time = T_YELLOW;
        S2: max_time = T_GREEN;
        S3: max_time = T_YELLOW;
        default: max_time = T_GREEN;
    endcase
end

always @(posedge clk or posedge rst) begin
    if (rst)
        timer <= 0;
    else if (timer == max_time - 1)
        timer <= 0;
    else
        timer <= timer + 1;
end

always @(*) begin
    case(current_state)
        S0: next_state = (timer == max_time-1) ? S1 : S0;
        S1: next_state = (timer == max_time-1) ? S2 : S1;
        S2: next_state = (timer == max_time-1) ? S3 : S2;
        S3: next_state = (timer == max_time-1) ? S0 : S3;
        default: next_state = S0;
    endcase
end

endmodule

tlc_tb.v
`timescale 1ns/1ps
`include "tlc.v"

module tlc_tb;
reg clk;
reg rst;
wire A_red, A_yellow, A_green;
wire B_red, B_yellow, B_green;

tlc uut (
    .clk(clk),
    .rst(rst),
    .A_red(A_red),
    .A_yellow(A_yellow),
    .A_green(A_green),
    .B_red(B_red),
    .B_yellow(B_yellow),
    .B_green(B_green)
);

initial begin
    clk = 0;
    forever #5 clk = ~clk;
end

initial begin
    $dumpfile("tlc.vcd");
    $dumpvars(0, tlc_tb);
    rst = 1;
    #20;
    rst = 0;
    #400;
    $finish;
end

// Safety Check: No Collision
always @(posedge clk) begin
    if (A_green && B_green) begin
        $display("ERROR: Collision detected at time %t", $time);
        $stop;
    end
end

initial begin
    $monitor("Time=%0t | A: R=%b Y=%b G=%b | B: R=%b Y=%b G=%b",
              $time,
              A_red, A_yellow, A_green,
              B_red, B_yellow, B_green);
end

endmodule

tlc.vcd
$date
	Wed Mar 04 23:49:55 2026
$end
$version
	Icarus Verilog
$end
$timescale
	1ps
$end
$scope module tlc_tb $end
$var wire 1 ! B_yellow $end
$var wire 1 " B_red $end
$var wire 1 # B_green $end
$var wire 1 $ A_yellow $end
$var wire 1 % A_red $end
$var wire 1 & A_green $end
$var reg 1 ' clk $end
$var reg 1 ( rst $end
$scope module uut $end
$var wire 1 ' clk $end
$var wire 1 ( rst $end
$var parameter 4 ) S0 $end
$var parameter 4 * S1 $end
$var parameter 4 + S2 $end
$var parameter 4 , S3 $end
$var parameter 32 - T_GREEN $end
$var parameter 32 . T_YELLOW $end
$var reg 1 & A_green $end
$var reg 1 % A_red $end
$var reg 1 $ A_yellow $end
$var reg 1 # B_green $end
$var reg 1 " B_red $end
$var reg 1 ! B_yellow $end
$var reg 4 / current_state [3:0] $end
$var reg 4 0 max_time [3:0] $end
$var reg 4 1 next_state [3:0] $end
$var reg 4 2 timer [3:0] $end
$upscope $end
$upscope $end
$enddefinitions $end
$comment Show the parameter values. $end
$dumpall
b11 .
b1010 -
b1000 ,
b100 +
b10 *
b1 )
$end
#0
$dumpvars
b0 2
b1 1
b1010 0
b1 /
1(
0'
1&
0%
0$
0#
1"
0!
$end
#5000
1'
#10000
0'
#15000
1'
#20000
0'
0(
#25000
b1 2
1'
#30000
0'
#35000
b10 2
1'
#40000
0'
#45000
b11 2
1'
#50000
0'
#55000
b100 2
1'
#60000
0'
#65000
b101 2
1'
#70000
0'
#75000
b110 2
1'
#80000
0'
#85000
b111 2
1'
#90000
0'
#95000
b1000 2
1'
#100000
0'
#105000
b10 1
b1001 2
1'
#110000
0'
#115000
1$
1"
0&
b11 0
b10 /
b0 2
1'
#120000
0'
#125000
b1 2
1'
#130000
0'
#135000
b100 1
b10 2
1'
#140000
0'
#145000
b1010 0
1#
1%
0"
0$
b0 2
b100 /
1'
#150000
0'
#155000
b1 2
1'
#160000
0'
#165000
b10 2
1'
#170000
0'
#175000
b11 2
1'
#180000
0'
#185000
b100 2
1'
#190000
0'
#195000
b101 2
1'
#200000
0'
#205000
b110 2
1'
#210000
0'
#215000
b111 2
1'
#220000
0'
#225000
b1000 2
1'
#230000
0'
#235000
b1000 1
b1001 2
1'
#240000
0'
#245000
1!
0#
1%
b11 0
b0 2
b1000 /
1'
#250000
0'
#255000
b1 2
1'
#260000
0'
#265000
b1 1
b10 2
1'
#270000
0'
#275000
b1010 0
1"
1&
0!
0%
b1 /
b0 2
1'
#280000
0'
#285000
b1 2
1'
#290000
0'
#295000
b10 2
1'
#300000
0'
#305000
b11 2
1'
#310000
0'
#315000
b100 2
1'
#320000
0'
#325000
b101 2
1'
#330000
0'
#335000
b110 2
1'
#340000
0'
#345000
b111 2
1'
#350000
0'
#355000
b1000 2
1'
#360000
0'
#365000
b10 1
b1001 2
1'
#370000
0'
#375000
1$
1"
0&
b11 0
b10 /
b0 2
1'
#380000
0'
#385000
b1 2
1'
#390000
0'
#395000
b100 1
b10 2
1'
#400000
0'
#405000
b1010 0
1#
1%
0"
0$
b0 2
b100 /
1'
#410000
0'
#415000
b1 2
1'
